Metadata-Version: 1.1
Name: base30-korean
Version: 0.0.2
Summary: crockford base32를 한국어 실정에 맞게 변형한 base30
Home-page: https://github.com/iz4blue/base30-korean
Author: Joseph Kim
Author-email: iz4blue@gmail.com
License: BSD
Platform: UNKNOWN
Classifier: Development Status :: 2 - Pre-Alpha
Classifier: Intended Audience :: Developers
Classifier: License :: OSI Approved :: BSD License
Classifier: Operating System :: OS Independent
Classifier: Programming Language :: Python :: 3.6
Classifier: Topic :: Software Development :: Libraries :: Python Modules
Classifier: Topic :: Utilities
Classifier: Natural Language :: Korean
